[{"content":"","date":"21 April 2026","externalUrl":null,"permalink":"/tags/ai/","section":"Tags","summary":"","title":"AI","type":"tags"},{"content":"Welcome. Recent posts are below; use the Posts link for the full archive.\n","date":"21 April 2026","externalUrl":null,"permalink":"/","section":"Hello","summary":"Welcome. Recent posts are below; use the Posts link for the full archive.\n","title":"Hello","type":"page"},{"content":"","date":"21 April 2026","externalUrl":null,"permalink":"/tags/networking/","section":"Tags","summary":"","title":"Networking","type":"tags"},{"content":"","date":"21 April 2026","externalUrl":null,"permalink":"/tags/philosophy/","section":"Tags","summary":"","title":"Philosophy","type":"tags"},{"content":"","date":"21 April 2026","externalUrl":null,"permalink":"/posts/","section":"Posts","summary":"","title":"Posts","type":"posts"},{"content":"","date":"21 April 2026","externalUrl":null,"permalink":"/tags/systems/","section":"Tags","summary":"","title":"Systems","type":"tags"},{"content":"","date":"21 April 2026","externalUrl":null,"permalink":"/tags/","section":"Tags","summary":"","title":"Tags","type":"tags"},{"content":"Note on authorship. This article was drafted with the assistance of an AI system. The ideas and framing are the author’s; the model helped with structure and wording. The prompt used to generate this piece appears below verbatim.\nPrompt # write a blog post titled: \u0026ldquo;When the weight of civilizations beats system design\u0026rdquo; mention first that the article is AI written, and give the prompt that I will give you here.\nThe idea of the post should describe what I call \u0026ldquo;organisation darwinism\u0026rdquo; . Sometimes, when building (IT) systems we tend to try to reinvent the wheel. Bring some new concepts thinking that the problem is new; but human, remained humans for years, decades, centuries and milleniums. After fixing their basic needs, and because they are a social specie, they started to organised and fixed upcoming issues slowly within the same timescale: first and foremost: communication. transmit information (the I in IT) , save it, improve it, etc\u0026hellip;. Legal issues also arise very early with the central concepts of liability, accountability, empathy fariness, equity and justice.\nSo, most to not say all of the issues that we are facing in today\u0026rsquo;s complex AI + IT world have been solved and refined for centuries. TCP, HTTP and SMTP are the first things that came to my mind when I have seen the parallel in the begining of my carreer. TCP as protocol is built as language: a set of rule to communicate and not interutp, HTTP as a library and SMTP as a postoffice.\nAI Agents will not make an exception to that. So today that we are facing issues with Authentication and Access Control for Agents, I just want to have a look at what already exist\nOrganisation darwinism # When we build IT systems, we often behave as if the problem were invented last Tuesday. We mint new nouns, draw fresh boxes on whiteboards, and reach for greenfield designs—while the hard part was never the syntax of our favourite language. It was coordination among people who do not share one brain.\nI call the longer view organisation darwinism: over millennia, after food and shelter, human societies repeatedly converged on the same pressures. We are a social species. We had to communicate, to remember, to dispute, and to assign responsibility when things went wrong. Those needs did not appear with Kubernetes. They appeared with the first market, the first contract, and the first time someone said, “You told me X, and I relied on it.”\nThe information age did not create information; it scaled it. The “I” in IT is still transmission, storage, and refinement of meaning—only faster pipes and cheaper clay tablets.\nLaw arrived early for the same reason protocols did: ambiguity is expensive. Liability, accountability, empathy, fairness, equity, and justice are not buzzwords from a slide deck; they are the accumulated answers to “what do we do when trust breaks?” Strip the branding from today’s AI governance debates and you will find the same questions courts and councils have been stress-testing for centuries.\nFamiliar shapes in unfamiliar stacks # Early in my career, the parallels were almost comically literal. TCP behaves like a language you agree to speak: turn-taking, acknowledgements, retransmission when meaning is lost—rules so that two parties can finish a sentence without talking over each other. HTTP felt like a library: you ask for a named resource; you receive a version; caching and redirects are the shelves and cross-references. SMTP felt like a post office: routing, envelopes, delivery attempts, bounce messages—society’s oldest asynchronous job queue.\nNone of these are perfect metaphors, but they are not accidents either. They encode social habits: politeness, addressing, provenance, retry, and failure semantics.\nAI agents inherit the same inheritance # AI agents will not get a pass from history. When we worry about authentication and access control for agents, we are not facing a wholly new species of problem. We are facing delegated action, identity, least privilege, audit trails, and liability—topics that legal systems and enterprises have refined the hard way.\nThat is an invitation, not a dismissal. The work ahead is to map agent behaviour onto durable patterns: who may act on whose behalf, for how long, under what scope, with what evidence, and with what rollback when the agent oversteps. The answers will borrow from OAuth and OpenID Connect, from RBAC and ABAC, from policy engines and service meshes, from contracts and from operational practice—not because those tools are sacred, but because they are the sediment of many failures.\nThe weight of civilizations is not romantic nostalgia. It is compressed trial and error. Before we reinvent the wheel, we should read the manual that humanity has been annotating since before we had packets.\nIf you are building in this space, the practical next step is simple: enumerate your agent’s powers the way you would enumerate API scopes; then ask who is accountable when it misuses them. The technology will change; the question will not.\n","date":"21 April 2026","externalUrl":null,"permalink":"/posts/2026-04-21-when-the-weight-of-civilizations-beats-system-design/","section":"Posts","summary":"A short essay on organisation darwinism: centuries of human coordination already shaped the patterns we now encode in protocols and law.","title":"When the weight of civilizations beats system design","type":"posts"},{"content":"After a long quiet stretch, I am picking the blog back up. Expect short, practical write-ups—mostly engineering notes, experiments, and the occasional story that ends in a stack trace.\nThanks for reading; more soon.\n","date":"20 April 2026","externalUrl":null,"permalink":"/posts/2026-04-20-back-to-posting/","section":"Posts","summary":"After a long quiet stretch, I am picking the blog back up again—this time on Hugo with the Blowfish theme.","title":"Back to posting","type":"posts"},{"content":"","date":"20 April 2026","externalUrl":null,"permalink":"/tags/meta/","section":"Tags","summary":"","title":"Meta","type":"tags"},{"content":"This site is where I publish notes and longer write-ups on software, systems, and tools I use day to day. Expect a mix of practical engineering detail, experiments that did not quite go to plan, and occasional commentary on how we build and run things.\nAbout me # I am Akram, a software engineer. I care about building reliable systems, clear interfaces between humans and machines, and writing that helps the next reader (including future me) move faster.\nI work across the stack and spend a lot of time on cloud-native platforms, automation, and lately more AI-assisted engineering and agent-style workflows in real codebases—not just demos.\nFor code and smaller experiments, I am usually on GitHub. For professional background and endorsements, see LinkedIn.\nContact # The easiest way to reach me for something public or technical is a GitHub issue or discussion on a relevant repository, or LinkedIn messages if that fits the context.\nIf you are reaching out about something sensitive, use LinkedIn or another channel we already share rather than posting personal details in comments.\nLegal # Privacy: This site is hosted on GitHub Pages. GitHub’s own privacy statement applies to hosting and traffic. I do not run first-party analytics on this domain; if that changes, this page will be updated. License: Unless a post or page says otherwise, original text on this site is licensed under CC BY 4.0 (you may share and adapt with attribution). Code snippets may be treated as MIT-0 / public domain unless explicitly marked—when in doubt, ask. ","externalUrl":null,"permalink":"/about/","section":"Hello","summary":"This site is where I publish notes and longer write-ups on software, systems, and tools I use day to day. Expect a mix of practical engineering detail, experiments that did not quite go to plan, and occasional commentary on how we build and run things.\nAbout me # I am Akram, a software engineer. I care about building reliable systems, clear interfaces between humans and machines, and writing that helps the next reader (including future me) move faster.\nI work across the stack and spend a lot of time on cloud-native platforms, automation, and lately more AI-assisted engineering and agent-style workflows in real codebases—not just demos.\nFor code and smaller experiments, I am usually on GitHub. For professional background and endorsements, see LinkedIn.\nContact # The easiest way to reach me for something public or technical is a GitHub issue or discussion on a relevant repository, or LinkedIn messages if that fits the context.\nIf you are reaching out about something sensitive, use LinkedIn or another channel we already share rather than posting personal details in comments.\nLegal # Privacy: This site is hosted on GitHub Pages. GitHub’s own privacy statement applies to hosting and traffic. I do not run first-party analytics on this domain; if that changes, this page will be updated. License: Unless a post or page says otherwise, original text on this site is licensed under CC BY 4.0 (you may share and adapt with attribution). Code snippets may be treated as MIT-0 / public domain unless explicitly marked—when in doubt, ask. ","title":"About","type":"page"},{"content":"","externalUrl":null,"permalink":"/authors/","section":"Authors","summary":"","title":"Authors","type":"authors"},{"content":"","externalUrl":null,"permalink":"/categories/","section":"Categories","summary":"","title":"Categories","type":"categories"},{"content":"","externalUrl":null,"permalink":"/series/","section":"Series","summary":"","title":"Series","type":"series"}]